{
  "identifier": "chambers_thomas",
  "iid": "chambers_thomas",
  "uid": 0,
  "worldX": 0,
  "worldY": 0,
  "worldDepth": 0,
  "pxWid": 480,
  "pxHei": 384,
  "bgColor": "#2a1a1a",
  "layerInstances": [
    {
      "__identifier": "Entities",
      "__type": "Entities",
      "__cWid": 15,
      "__cHei": 12,
      "__gridSize": 32,
      "entityInstances": [
        {
          "__identifier": "PlayerSpawn",
          "__grid": [
            7,
            10
          ],
          "__pivot": [
            0.5,
            1
          ],
          "__tags": [],
          "__tile": null,
          "__worldX": 240,
          "__worldY": 352,
          "defUid": 1,
          "iid": "spawn_main",
          "width": 32,
          "height": 32,
          "px": [
            224,
            320
          ],
          "fieldInstances": []
        },
        {
          "__identifier": "NPC",
          "__grid": [
            7,
            4
          ],
          "__pivot": [
            0.5,
            1
          ],
          "__tags": [],
          "__tile": null,
          "__worldX": 240,
          "__worldY": 160,
          "defUid": 2,
          "iid": "npc_thomas",
          "width": 32,
          "height": 32,
          "px": [
            224,
            128
          ],
          "fieldInstances": [
            {
              "__identifier": "name",
              "__type": "String",
              "__value": "Justice Thomas",
              "defUid": 0,
              "realEditorValues": []
            },
            {
              "__identifier": "characterId",
              "__type": "String",
              "__value": "npc.justice_thomas",
              "defUid": 0,
              "realEditorValues": []
            },
            {
              "__identifier": "storyKnot",
              "__type": "String",
              "__value": "justice_thomas_intro",
              "defUid": 0,
              "realEditorValues": []
            }
          ]
        },
        {
          "__identifier": "EncounterTrigger",
          "__grid": [
            7,
            4
          ],
          "__pivot": [
            0.5,
            1
          ],
          "__tags": [],
          "__tile": null,
          "__worldX": 240,
          "__worldY": 160,
          "defUid": 3,
          "iid": "encounter_thomas",
          "width": 32,
          "height": 32,
          "px": [
            224,
            128
          ],
          "fieldInstances": [
            {
              "__identifier": "justiceId",
              "__type": "String",
              "__value": "justice_thomas",
              "defUid": 0,
              "realEditorValues": []
            },
            {
              "__identifier": "name",
              "__type": "String",
              "__value": "Justice Thomas",
              "defUid": 0,
              "realEditorValues": []
            },
            {
              "__identifier": "deckTag",
              "__type": "String",
              "__value": "evidence",
              "defUid": 0,
              "realEditorValues": []
            },
            {
              "__identifier": "count",
              "__type": "Int",
              "__value": 5,
              "defUid": 0,
              "realEditorValues": []
            },
            {
              "__identifier": "rewardId",
              "__type": "String",
              "__value": "evidence_blazer",
              "defUid": 0,
              "realEditorValues": []
            },
            {
              "__identifier": "once",
              "__type": "Bool",
              "__value": true,
              "defUid": 0,
              "realEditorValues": []
            }
          ]
        },
        {
          "__identifier": "Prop",
          "__grid": [
            7,
            1
          ],
          "__pivot": [
            0.5,
            1
          ],
          "__tags": [],
          "__tile": null,
          "__worldX": 240,
          "__worldY": 64,
          "defUid": 4,
          "iid": "prop_evidence_board__wall_props__1",
          "width": 32,
          "height": 32,
          "px": [
            224,
            32
          ],
          "fieldInstances": [
            {
              "__identifier": "sprite",
              "__type": "String",
              "__value": "prop.evidence_board",
              "defUid": 0,
              "realEditorValues": []
            },
            {
              "__identifier": "collision",
              "__type": "Bool",
              "__value": false,
              "defUid": 0,
              "realEditorValues": []
            },
            {
              "__identifier": "propId",
              "__type": "String",
              "__value": "prop.evidence_board",
              "defUid": 0,
              "realEditorValues": []
            }
          ]
        },
        {
          "__identifier": "Prop",
          "__grid": [
            7,
            5
          ],
          "__pivot": [
            0.5,
            1
          ],
          "__tags": [],
          "__tile": null,
          "__worldX": 240,
          "__worldY": 192,
          "defUid": 5,
          "iid": "prop_tape_recorder__desk_zone__2",
          "width": 32,
          "height": 32,
          "px": [
            224,
            160
          ],
          "fieldInstances": [
            {
              "__identifier": "sprite",
              "__type": "String",
              "__value": "prop.tape_recorder",
              "defUid": 0,
              "realEditorValues": []
            },
            {
              "__identifier": "collision",
              "__type": "Bool",
              "__value": false,
              "defUid": 0,
              "realEditorValues": []
            },
            {
              "__identifier": "propId",
              "__type": "String",
              "__value": "prop.tape_recorder",
              "defUid": 0,
              "realEditorValues": []
            }
          ]
        }
      ]
    },
    {
      "__identifier": "Collisions",
      "__type": "IntGrid",
      "__cWid": 15,
      "__cHei": 12,
      "__gridSize": 32,
      "intGridCsv": [
        0,
        0,
        0,
        0,
        0,
        0,
        0,
        0,
        0,
        0,
        0,
        0,
        0,
        0,
        0,
        0,
        0,
        0,
        0,
        0,
        0,
        0,
        0,
        0,
        0,
        0,
        0,
        0,
        0,
        0,
        0,
        0,
        0,
        0,
        0,
        0,
        0,
        0,
        0,
        0,
        0,
        0,
        0,
        0,
        0,
        0,
        0,
        0,
        0,
        0,
        0,
        0,
        0,
        0,
        0,
        0,
        0,
        0,
        0,
        0,
        0,
        0,
        0,
        0,
        0,
        0,
        0,
        0,
        0,
        0,
        0,
        0,
        0,
        0,
        0,
        0,
        0,
        0,
        0,
        0,
        0,
        0,
        0,
        0,
        0,
        0,
        0,
        0,
        0,
        0,
        0,
        0,
        0,
        0,
        0,
        0,
        0,
        0,
        0,
        0,
        0,
        0,
        0,
        0,
        0,
        0,
        0,
        0,
        0,
        0,
        0,
        0,
        0,
        0,
        0,
        0,
        0,
        0,
        0,
        0,
        0,
        0,
        0,
        0,
        0,
        0,
        0,
        0,
        0,
        0,
        0,
        0,
        0,
        0,
        0,
        0,
        0,
        0,
        0,
        0,
        0,
        0,
        0,
        0,
        0,
        0,
        0,
        0,
        0,
        0,
        0,
        0,
        0,
        0,
        0,
        0,
        0,
        0,
        0,
        0,
        0,
        0,
        0,
        0,
        0,
        0,
        0,
        0,
        0,
        0,
        0,
        0,
        0,
        0,
        0,
        0,
        0,
        0,
        0,
        0
      ],
      "autoLayerTiles": [],
      "gridTiles": [],
      "entityInstances": []
    },
    {
      "__identifier": "Floor",
      "__type": "IntGrid",
      "__cWid": 15,
      "__cHei": 12,
      "__gridSize": 32,
      "intGridCsv": [
        1,
        1,
        1,
        1,
        1,
        1,
        1,
        1,
        1,
        1,
        1,
        1,
        1,
        1,
        1,
        1,
        1,
        1,
        1,
        1,
        1,
        1,
        1,
        1,
        1,
        1,
        1,
        1,
        1,
        1,
        1,
        1,
        1,
        1,
        1,
        1,
        1,
        1,
        1,
        1,
        1,
        1,
        1,
        1,
        1,
        1,
        1,
        1,
        1,
        1,
        1,
        1,
        1,
        1,
        1,
        1,
        1,
        1,
        1,
        1,
        1,
        1,
        1,
        1,
        1,
        1,
        1,
        1,
        1,
        1,
        1,
        1,
        1,
        1,
        1,
        1,
        1,
        1,
        1,
        1,
        1,
        1,
        1,
        1,
        1,
        1,
        1,
        1,
        1,
        1,
        1,
        1,
        1,
        1,
        1,
        1,
        1,
        1,
        1,
        1,
        1,
        1,
        1,
        1,
        1,
        1,
        1,
        1,
        1,
        1,
        1,
        1,
        1,
        1,
        1,
        1,
        1,
        1,
        1,
        1,
        1,
        1,
        1,
        1,
        1,
        1,
        1,
        1,
        1,
        1,
        1,
        1,
        1,
        1,
        1,
        1,
        1,
        1,
        1,
        1,
        1,
        1,
        1,
        1,
        1,
        1,
        1,
        1,
        1,
        1,
        1,
        1,
        1,
        1,
        1,
        1,
        1,
        1,
        1,
        1,
        1,
        1,
        1,
        1,
        1,
        1,
        1,
        1,
        1,
        1,
        1,
        1,
        1,
        1,
        1,
        1,
        1,
        1,
        1,
        1
      ],
      "autoLayerTiles": [],
      "gridTiles": [],
      "entityInstances": []
    }
  ],
  "_kimbar": {
    "name": "Justice Thomas's Chambers",
    "description": "The private chambers of Justice Thomas - Evidence challenge",
    "tileset": "courthouse",
    "music": "chambers_ambient",
    "connections": [
      {
        "direction": "south",
        "targetRoom": "scotus_hall_01"
      }
    ]
  }
}